qdep/__init__.py
qdep/qdep.py
qdep/internal/__init__.py
qdep/internal/cli.py
qdep/internal/common.py
qdep/internal/prf.py
qdep/internal/private.py
qdep-1.1.1.dist-info/LICENSE
qdep-1.1.1.dist-info/METADATA
qdep-1.1.1.dist-info/WHEEL
qdep-1.1.1.dist-info/entry_points.txt
qdep-1.1.1.dist-info/top_level.txt
qdep-1.1.1.dist-info/RECORD
