Metadata-Version: 2.1
Name: qdep
Version: 1.1.1
Summary: A very basic yet simple to use dependency management tool for qmake based projects
Home-page: https://github.com/Skycoder42/qdep
Author: Skycoder42
Author-email: skycoder42.de@gmx.de
License: UNKNOWN
Platform: UNKNOWN
Classifier: Programming Language :: Python :: 3
Classifier: License :: OSI Approved :: BSD License
Classifier: Operating System :: OS Independent
Requires-Dist: appdirs
Requires-Dist: lockfile
Requires-Dist: argcomplete
